spheremri/__init__.py
spheremri/cli.py
spheremri/dinov2s.pt
spheremri/model_selector.py
spheremri/rater.py
spheremri/t1_anchor.pt
spheremri/tse_anchor.pt
spheremri-0.1.0.dist-info/LICENSE
spheremri-0.1.0.dist-info/METADATA
spheremri-0.1.0.dist-info/WHEEL
spheremri-0.1.0.dist-info/entry_points.txt
spheremri-0.1.0.dist-info/top_level.txt
spheremri-0.1.0.dist-info/RECORD
