Metadata-Version: 2.1
Name: spheremri
Version: 0.1.0
Summary: MRI motion artifact rating tool
Home-page: https://github.com/jinghangli98/sphereMRI
Author: Jinghan Li
Author-email: jinghang.li@pitt.edu
Classifier: Programming Language :: Python :: 3
Classifier: License :: OSI Approved :: MIT License
Classifier: Operating System :: OS Independent
Requires-Python: >=3.7
License-File: LICENSE
Requires-Dist: torch (>=1.7.0)
Requires-Dist: torchvision (>=0.8.0)
Requires-Dist: numpy (>=1.19.0)
Requires-Dist: pillow (>=8.0.0)
Requires-Dist: nibabel (>=3.2.0)
Requires-Dist: tqdm (>=4.50.0)
